geo_encodings/__init__.py
geo_encodings/encoders.py
geo_encodings/utilities.py
geo_encodings-1.0.4.dist-info/licenses/LICENSE
geo_encodings-1.0.4.dist-info/WHEEL
geo_encodings-1.0.4.dist-info/METADATA
geo_encodings-1.0.4.dist-info/RECORD
