Metadata-Version: 2.4
Name: geo-encodings
Version: 1.0.4
Summary: Encodings for geometric objects
Keywords: geospatial,artificial intelligence,machine learning,encoding
Author-email: John Collins <john@odyssey-geospatial.com>
License-File: LICENSE
Requires-Dist: shapely
Requires-Dist: scipy
Requires-Dist: numpy
